recipescraper/__init__.py
recipescraper/main.py
recipescraper/utils/__init__.py
recipescraper/utils/get_data.py
recipescraper/utils/write_data.py
recipescraper_cli_tool_er-0.1.1.dist-info/METADATA
recipescraper_cli_tool_er-0.1.1.dist-info/WHEEL
recipescraper_cli_tool_er-0.1.1.dist-info/entry_points.txt
recipescraper_cli_tool_er-0.1.1.dist-info/top_level.txt
recipescraper_cli_tool_er-0.1.1.dist-info/RECORD
