Metadata-Version: 2.4
Name: recipescraper-cli-tool-er
Version: 0.1.1
Summary: Add your description here
Requires-Python: >=3.13
Requires-Dist: argparse>=1.4.0
Requires-Dist: bs4>=0.0.2
Requires-Dist: requests>=2.32.5
Requires-Dist: validators>=0.35.0
